Filchatter/__init__.py
Filchatter/filchatter.py
filchatter-2.0.dist-info/LICENSE.md
filchatter-2.0.dist-info/METADATA
filchatter-2.0.dist-info/WHEEL
filchatter-2.0.dist-info/entry_points.txt
filchatter-2.0.dist-info/top_level.txt
filchatter-2.0.dist-info/RECORD
