Metadata-Version: 2.1
Name: filchatter
Version: 2.0
License-File: LICENSE.md
Requires-Dist: requests
